rumorz/__init__.py
rumorz/client.py
rumorz/copilot.py
rumorz/encoder.py
rumorz/enums.py
rumorz/streamlit_app/__init__.py
rumorz/streamlit_app/streamlit_app.py
rumorz/tests/__init__.py
rumorz/tests/test_sdk.py
rumorz-0.1.15.dist-info/LICENSE
rumorz-0.1.15.dist-info/METADATA
rumorz-0.1.15.dist-info/WHEEL
rumorz-0.1.15.dist-info/top_level.txt
rumorz-0.1.15.dist-info/RECORD
