Metadata-Version: 2.1
Name: rumorz
Version: 0.1.15
Summary: Rumorz.io official Python SDK
Author-email: Othmane Zoheir <othmane@rumorz.io>
Project-URL: Homepage, https://github.com/rumorz-ai/rumorz
Project-URL: Issues, https://github.com/rumorz-ai/rumorz/issues
Classifier: Programming Language :: Python :: 3
Classifier: License :: OSI Approved :: MIT License
Classifier: Operating System :: OS Independent
Requires-Python: >=3.8
License-File: LICENSE
Requires-Dist: pandas
Requires-Dist: numpy
Requires-Dist: psutil
Requires-Dist: requests
Requires-Dist: litellm
